obs/__init__.py
obs/auth.py
obs/bucket.py
obs/bulktasks.py
obs/cache.py
obs/client.py
obs/const.py
obs/convertor.py
obs/extension.py
obs/http2.py
obs/ilog.py
obs/loadtoken.py
obs/locks.py
obs/model.py
obs/progress.py
obs/searchmethod.py
obs/transfer.py
obs/util.py
obs/workflow.py
alphanetworks_obs_py-3.20.7.1.dist-info/METADATA
alphanetworks_obs_py-3.20.7.1.dist-info/WHEEL
alphanetworks_obs_py-3.20.7.1.dist-info/top_level.txt
alphanetworks_obs_py-3.20.7.1.dist-info/RECORD
