Metadata-Version: 2.1
Name: alphanetworks-obs-py
Version: 3.20.7.1
Summary: OBS Python SDK
Home-page: UNKNOWN
Author: UNKNOWN
Author-email: UNKNOWN
License: Apache-2.0
Keywords: obs,python,alphanetworks
Platform: Independant
